quarkupy/__init__.py
quarkupy/_base_client.py
quarkupy/_client.py
quarkupy/_compat.py
quarkupy/_constants.py
quarkupy/_exceptions.py
quarkupy/_files.py
quarkupy/_models.py
quarkupy/_qs.py
quarkupy/_resource.py
quarkupy/_response.py
quarkupy/_streaming.py
quarkupy/_types.py
quarkupy/_version.py
quarkupy/py.typed
quarkupy/_utils/__init__.py
quarkupy/_utils/_logs.py
quarkupy/_utils/_proxy.py
quarkupy/_utils/_reflection.py
quarkupy/_utils/_resources_proxy.py
quarkupy/_utils/_streams.py
quarkupy/_utils/_sync.py
quarkupy/_utils/_transform.py
quarkupy/_utils/_typing.py
quarkupy/_utils/_utils.py
quarkupy/lib/.keep
quarkupy/lib/__init__.py
quarkupy/lib/agent/__init__.py
quarkupy/lib/agent/knowledge_agent.py
quarkupy/lib/context/__init__.py
quarkupy/lib/context/manager.py
quarkupy/lib/runner/__init__.py
quarkupy/lib/runner/driver.py
quarkupy/lib/runner/inputs.py
quarkupy/lib/runner/quarks.py
quarkupy/resources/__init__.py
quarkupy/resources/authorize.py
quarkupy/resources/dataset.py
quarkupy/resources/json_schemas.py
quarkupy/resources/sources.py
quarkupy/resources/users.py
quarkupy/resources/admin/__init__.py
quarkupy/resources/admin/admin.py
quarkupy/resources/admin/identity/__init__.py
quarkupy/resources/admin/identity/identity.py
quarkupy/resources/admin/identity/identity_.py
quarkupy/resources/admin/identity/roles/__init__.py
quarkupy/resources/admin/identity/roles/roles.py
quarkupy/resources/admin/identity/roles/members/__init__.py
quarkupy/resources/admin/identity/roles/members/identity.py
quarkupy/resources/admin/identity/roles/members/members.py
quarkupy/resources/admin/identity/roles/members/role.py
quarkupy/resources/context/__init__.py
quarkupy/resources/context/classifiers.py
quarkupy/resources/context/context.py
quarkupy/resources/context/extractors.py
quarkupy/resources/history/__init__.py
quarkupy/resources/history/flow.py
quarkupy/resources/history/history.py
quarkupy/resources/history/quark.py
quarkupy/resources/models/__init__.py
quarkupy-0.7.0.dist-info/METADATA
quarkupy-0.7.0.dist-info/WHEEL
quarkupy-0.7.0.dist-info/licenses/LICENSE
quarkupy-0.7.0.dist-info/RECORD
