Metadata-Version: 2.3
Name: quarkupy
Version: 0.7.0
Summary: The official Python library for the quark API
Project-URL: Homepage, https://github.com/quarklabsai/quarkupy
Project-URL: Repository, https://github.com/quarklabsai/quarkupy
Author: Quark
License: Apache-2.0
Classifier: Intended Audience :: Developers
Classifier: License :: OSI Approved :: Apache Software License
Classifier: Operating System :: MacOS
Classifier: Operating System :: Microsoft :: Windows
Classifier: Operating System :: OS Independent
Classifier: Operating System :: POSIX
Classifier: Operating System :: POSIX :: Linux
Classifier: Programming Language :: Python :: 3.8
Classifier: Programming Language :: Python :: 3.9
Classifier: Programming Language :: Python :: 3.10
Classifier: Programming Language :: Python :: 3.11
Classifier: Programming Language :: Python :: 3.12
Classifier: Topic :: Software Development :: Libraries :: Python Modules
Classifier: Typing :: Typed
Requires-Python: >=3.8
Requires-Dist: anyio<5,>=3.5.0
Requires-Dist: distro<2,>=1.7.0
Requires-Dist: halo>=0.0.31
Requires-Dist: httpx<1,>=0.23.0
Requires-Dist: pandas>=2.0.3
Requires-Dist: pyarrow>=17.0.0
Requires-Dist: pydantic<3,>=1.9.0
Requires-Dist: python-dotenv>=1.0.1
Requires-Dist: sniffio
Requires-Dist: typing-extensions<5,>=4.10
Requires-Dist: uuid-utils>=0.9.0
Provides-Extra: aiohttp
Requires-Dist: aiohttp; extra == 'aiohttp'
Requires-Dist: httpx-aiohttp>=0.1.6; extra == 'aiohttp'
